{"LVS_T1IN":{"type":"DOVAR_HMI","descr":"клапан набору Т1","adr":0},"LVS_T2IN":{"type":"DOVAR_HMI","descr":"клапан набору Т2","adr":1},"LVS_T1OUT":{"type":"DOVAR_HMI","descr":"клапан зливу Т1","adr":2},"LVS_T2OUT":{"type":"DOVAR_HMI","descr":"клапан зливу Т2","adr":3},"LVS_D1IN":{"type":"DOVAR_HMI","descr":"клапан набору D1","adr":4},"LVS_D2IN":{"type":"DOVAR_HMI","descr":"клапан набору D2","adr":5},"LVS_D1OUT":{"type":"DOVAR_HMI","descr":"клапан зливу D1","adr":6},"LVS_D2OUT":{"type":"DOVAR_HMI","descr":"клапан зливу D2","adr":7},"XVS_T1T2":{"type":"DOVAR_HMI","descr":"3-ходовий клапан T1-T2","adr":8},"NS_M1":{"type":"DOVAR_HMI","descr":"пускач двигуна мішалки Т1","adr":9},"NS_M2":{"type":"DOVAR_HMI","descr":"пускач двигуна мішалки Т2","adr":10}}